{
  "arch": "x86_64",
  "build": "py312haa95532_0",
  "build_number": 0,
  "channel": "https://repo.anaconda.com/pkgs/main/",
  "constrains": [],
  "depends": [
    "python >=3.12,<3.13.0a0"
  ],
  "fn": "boltons-24.1.0-py312haa95532_0.conda",
  "license": "BSD-3-Clause",
  "license_family": "BSD",
  "md5": "e5340714a5985d954159ca911f93c91c",
  "name": "boltons",
  "platform": "win32",
  "sha256": "122e4faed0379d8864f435c3664f4b03b091a297a2db8ae8c544457d488052eb",
  "size": 493870,
  "subdir": "win-64",
  "timestamp": 1737062132000,
  "url": "https://repo.anaconda.com/pkgs/main/win-64/boltons-24.1.0-py312haa95532_0.conda",
  "version": "24.1.0"
}